src/design.sv
// Code your design here
// Code your design here


module maj3( OUT, A, B, C);
	
  input A, B, C;
  output OUT;
  wire AB, BC, CA;
  
  
  and( AB, A, B);
  and( BC, B, C); //instantiation of and() gate
  and( CA, C, A);
  // comment
 
  or( OUT, AB, BC, CA); 
endmodule

test/testbench.sv
// Code your testbench here
// or browse Examples
 
module maj3_tb;
  
  //dont take inputs dont produce outputs
//they need design under test 


//DUT - chip, 3 lines in, 1 out
//Test bench - Bread Board

  //3 local(wires of BB/probe) pins and 1 out part of test bench not part of DUT.

//wire local to test bench
  reg a, b, c;
  wire out;
  
  // not function call, instantiation
  maj3 DUT1( out, a, b, c);
  
  //values for a, b c enum
  initial begin 
    for( int i= 0; i<8; i++) begin
      #5 {a,b,c} = i; // each bit of i is assigned to a, b, c i2, i1, i0, 3bits
      //every 5 time units, value changes
    end  
  end
  
  //i-verilog compiler under use.
  
  initial begin
    $monitor(a,b,c, out);
    $dumpfile("dump.vcd");//waveform file value change dump
    $dumpvars; //to dump all vars
	end
endmodule

test/dump.vcd
$date
	Mon Nov 28 10:39:41 2022
$end
$version
	Icarus Verilog
$end
$timescale
	1s
$end
$scope module maj3_tb $end
$var wire 1 ! out $end
$var reg 1 " a $end
$var reg 1 # b $end
$var reg 1 $ c $end
$scope module DUT1 $end
$var wire 1 " A $end
$var wire 1 % AB $end
$var wire 1 # B $end
$var wire 1 & BC $end
$var wire 1 $ C $end
$var wire 1 ' CA $end
$var wire 1 ! OUT $end
$upscope $end
$scope begin $ivl_for_loop0 $end
$var integer 32 ( i [31:0] $end
$upscope $end
$upscope $end
$enddefinitions $end
#0
$dumpvars
b0 (
x'
x&
x%
x$
x#
x"
x!
$end
#5
0!
0%
0&
0'
b1 (
0"
0#
0$
#10
b10 (
1$
#15
b11 (
1#
0$
#20
1!
1&
b100 (
1$
#25
0!
0&
b101 (
1"
0#
0$
#30
1!
1'
b110 (
1$
#35
1%
0'
b111 (
1#
0$
#40
1&
1'
b1000 (
1$
