dataPathCtrlPathDesign/src/dataCtrlDesignMulUsingAdd_IitKrgpr.sv
`include "behavioural_PIPO1.sv"
`include "behavioural_PIPO2.sv"
`include "behavioural_ADD16.sv"
`include "behavioural_EQZ.sv"
`include "behavioural_CNTR.sv"

module MUL_dataPath( eqz, ldA, ldB, ldP, clrP, decB, data_in, clk);
	input ldA, ldB, ldP, clrP, decB, clk;
	input [15:0] data_in;
	output eqz;
	wire [15:0] x, y, z, bOut, bus;

	//data path instantiation 
	assign bus = data_in;
	
	//instantiations	
	PIPO1 A (x, bus, ldA, clk); //parallel-in parallel-out without clr  
    PIPO2 P (y, z, ldP, clrP, clk); //parallel-in parallel-out with clr 
	CNTR B ( bOut, bus, ldB, decB, clk); //counter
	ADD AD ( z, x, y); //adder
	EQZ COMP ( eqz, bOut); //comparator

endmodule // Code your design here

module controller( ldA, ldB, ldP, clrP, decB, done, clk, eqz, start);
	input clk, eqz, start;
	output reg ldA, ldB, ldP, clrP, decB, done; //controller will be generating these signals. output signals 
	reg [2:0]state; //s0, s1, s2, s3, s4
	parameter S0 = 3'b000, S1 = 3'b001, S2 = 3'b010, S3 = 3'b011, S4 = 3'b100;
	always @( posedge clk)
	begin 
		case (state)
			S0: if(start) state <= S1;
			S1: state <= S2;
			S2: state <= S3;
			S3: #2 if(eqz) state <= S4; //delay for sync
			S4: state <= S4;
			default: state <= S0;
		endcase
	end

	always @ ( state )
	begin
		case(state)
			S0: begin #1 
				ldA = 0; ldB = 0; ldP = 0;
				clrP = 0; decB = 0; 
			    	end
		        S1: begin #1
				ldA = 1;
			    	end
			S2: begin #1
			    ldA = 0; ldB = 1; clrP = 1; 
			 	end
		        S3: begin #1
	    			ldB = 0; ldP =1; clrP = 0;
				decB = 1; //P =  x + z, B = B-1, S3 repeated clock after  clock
				end	
			S4: begin #1
				done = 1; ldB = 0; ldP = 0;
				decB = 0;
				end
			default: begin #1
				ldA = 0; ldB = 0; ldP = 0; clrP = 0;
				decB = 0; 
				end
		endcase
	end
endmodule

dataPathCtrlPathDesign/src/behavioural_EQZ.sv
module EQZ( eqz, data);
	input [15:0] data;
	output eqz;
	assign eqz = (data == 0);
endmodule

dataPathCtrlPathDesign/src/behavioural_ADD16.sv
module ADD( out, in1, in2 );
	input [15:0] in1, in2;
	output reg [15:0]out;
	always @( * )
		out = in1 + in2;
endmodule

dataPathCtrlPathDesign/src/behavioural_CNTR.sv
module CNTR( dout, din, ld, dec, clk);
	input [15:0] din;
	input ld, dec, clk;
	output reg [15:0] dout;

	always @ ( posedge clk)
	if(ld )	dout <= din;
	else if(dec) dout <= dout -1;
endmodule

dataPathCtrlPathDesign/src/behavioural_PIPO2.sv
module PIPO2 ( dout, din, ld, clr ,clk );
	input [15:0] din;
	input ld, clr, clk;
	output reg [15:0] dout;
	
	always @(posedge clk)
		if( clr ) dout <= 16'b0;
		else if ( ld ) dout <= din;

endmodule

dataPathCtrlPathDesign/src/behavioural_PIPO1.sv
module PIPO1( dout, din, ld, clk);
	input ld, clk;
	input [15:0] din; //16-bit data
	output reg [15:0] dout;

	always @( posedge clk)
		if(ld) dout <= din;
endmodule

dataPathCtrlPathDesign/test/dataCtrlTestBenchMulUsingAdd_IitKrgpr.sv
// Code your testbench here
// or browse Examples
module MUL_dataPath_tb; 
	reg [15:0] data_in;
	reg clk, start;
	wire done;

	//DUTs:
	MUL_dataPath DP ( eqz, ldA, ldB, ldP, clrP, decB, data_in, clk );
	controller CON( ldA, ldB, ldP, clrP, decB, done, clk, eqz, start);

	initial 
		begin
			clk  = 1'b0;
			#3 start = 1'b1;
			#500 $finish;
		end
	always #5 clk = ~clk;
	initial
		begin
			#17 data_in = 17; //17  * 5 = 85
			#10 data_in = 5;
		end
	initial
		begin
		  $monitor ($time, " %d, %b", DP.y, done ); //y output of the product, accessing y from DP
          $dumpfile ("mul.vcd"); 
          $dumpvars;
		end
endmodule

dataPathCtrlPathDesign/test/mul.vcd
$date
	Sun Jan  8 19:22:38 2023
$end
$version
	Icarus Verilog
$end
$timescale
	1s
$end
$scope module MUL_dataPath_tb $end
$var wire 1 ! clrP $end
$var wire 1 " decB $end
$var wire 1 # done $end
$var wire 1 $ eqz $end
$var wire 1 % ldA $end
$var wire 1 & ldB $end
$var wire 1 ' ldP $end
$var reg 1 ( clk $end
$var reg 16 ) data_in [15:0] $end
$var reg 1 * start $end
$scope module DP $end
$var wire 16 + bOut [15:0] $end
$var wire 16 , bus [15:0] $end
$var wire 1 - clk $end
$var wire 1 ! clrP $end
$var wire 16 . data_in [15:0] $end
$var wire 1 " decB $end
$var wire 1 $ eqz $end
$var wire 1 % ldA $end
$var wire 1 & ldB $end
$var wire 1 ' ldP $end
$var wire 16 / x [15:0] $end
$var wire 16 0 y [15:0] $end
$var wire 16 1 z [15:0] $end
$scope module A $end
$var wire 1 - clk $end
$var wire 16 2 din [15:0] $end
$var wire 1 % ld $end
$var reg 16 3 dout [15:0] $end
$upscope $end
$scope module P $end
$var wire 1 - clk $end
$var wire 1 ! clr $end
$var wire 16 4 din [15:0] $end
$var wire 1 ' ld $end
$var reg 16 5 dout [15:0] $end
$upscope $end
$scope module B $end
$var wire 1 - clk $end
$var wire 1 " dec $end
$var wire 16 6 din [15:0] $end
$var wire 1 & ld $end
$var reg 16 7 dout [15:0] $end
$upscope $end
$scope module AD $end
$var wire 16 8 in1 [15:0] $end
$var wire 16 9 in2 [15:0] $end
$var reg 16 : out [15:0] $end
$upscope $end
$scope module COMP $end
$var wire 16 ; data [15:0] $end
$var wire 1 $ eqz $end
$upscope $end
$upscope $end
$scope module CON $end
$var wire 1 - clk $end
$var wire 1 $ eqz $end
$var wire 1 < start $end
$var reg 1 = clrP $end
$var reg 1 > decB $end
$var reg 1 ? done $end
$var reg 1 @ ldA $end
$var reg 1 A ldB $end
$var reg 1 B ldP $end
$var reg 3 C state [2:0] $end
$upscope $end
$upscope $end
$enddefinitions $end
#0
$dumpvars
bx C
xB
xA
x@
x?
x>
x=
x<
bx ;
bx :
bx 9
bx 8
bx 7
bx 6
bx 5
bx 4
bx 3
bx 2
bx 1
bx 0
bx /
bx .
0-
bx ,
bx +
x*
bx )
0(
x'
x&
x%
x$
x#
x"
x!
$end
#3
1*
1<
#5
b0 C
1(
1-
#6
0>
0"
0=
0!
0B
0'
0A
0&
0@
0%
#10
0(
0-
#15
b1 C
1(
1-
#16
1@
1%
#17
b10001 )
b10001 ,
b10001 2
b10001 6
b10001 .
#20
0(
0-
#25
b10001 3
b10001 /
b10001 8
b10 C
1(
1-
#26
1=
1!
1A
1&
0@
0%
#27
b101 )
b101 ,
b101 2
b101 6
b101 .
#30
0(
0-
#35
b10001 :
b10001 1
b10001 4
b11 C
b101 7
0$
b101 +
b101 ;
b0 5
b0 0
b0 9
1(
1-
#36
1>
1"
0=
0!
1B
1'
0A
0&
#40
0(
0-
#45
b100010 :
b100010 1
b100010 4
b10001 5
b10001 0
b10001 9
b100 7
b100 +
b100 ;
1(
1-
#50
0(
0-
#55
b110011 :
b110011 1
b110011 4
b11 7
b11 +
b11 ;
b100010 5
b100010 0
b100010 9
1(
1-
#60
0(
0-
#65
b1000100 :
b1000100 1
b1000100 4
b110011 5
b110011 0
b110011 9
b10 7
b10 +
b10 ;
1(
1-
#70
0(
0-
#75
b1010101 :
b1010101 1
b1010101 4
b1 7
b1 +
b1 ;
b1000100 5
b1000100 0
b1000100 9
1(
1-
#80
0(
0-
#85
b1100110 :
b1100110 1
b1100110 4
b1010101 5
b1010101 0
b1010101 9
b0 7
1$
b0 +
b0 ;
1(
1-
#87
b100 C
#88
0>
0"
0B
0'
1?
1#
